{
  "artist": "Felipe Rodrigues",
  "title": "Me Rendo a Ti",
  "tone": "C",
  "lyrics": "Diante da Tua presença\nEu me rendo a Ti, Senhor\nNão tenho nada a oferecer\nSenão o meu amor\n\nMe rendo a Ti\nMe rendo a Ti\nToma o meu coração\nFaz a Tua vontade em mim\n\nEu largo tudo aos Teus pés\nAs minhas forças já se foram\nMas na fraqueza Tu és forte\nE as Tuas mãos me sustentam\n\nMe rendo a Ti\nMe rendo a Ti\nToma o meu coração\nFaz a Tua vontade em mim\n\nNão quero mais o meu caminho\nQuero andar na Tua direção\nRendido estou aos Teus pés\nMolda o meu coração\n\nMe rendo a Ti\nMe rendo a Ti\nToma o meu coração\nFaz a Tua vontade em mim\n\nTudo que eu sou\nTudo que eu tenho\nEstá nas Tuas mãos, Senhor\nMe rendo a Ti\nMe rendo a Ti\nPra sempre meu Senhor\n\nMe rendo a Ti\nMe rendo a Ti\nToma o meu coração\nFaz a Tua vontade em mim\n\nMe rendo a Ti\nMe rendo a Ti",
  "tags": ["rendição", "entrega", "intimidade", "adoração"]
}
