{
  "artist": "Fernandinho",
  "title": "Apenas um Toque",
  "tone": "A",
  "lyrics": "Apenas um toque, Senhor\nÉ tudo que eu preciso\nApenas um toque da Tua mão\nE tudo vai mudar\n\nA mulher do fluxo de sangue\nTocou na orla da Tua veste\nE foi curada naquele instante\nApenas um toque\n\nApenas um toque, Senhor\nÉ tudo que eu preciso\nApenas um toque da Tua mão\nE tudo vai mudar\n\nOs cegos voltaram a ver\nOs surdos voltaram a ouvir\nOs coxos saltaram de alegria\nCom apenas um toque Teu\n\nApenas um toque, Senhor\nÉ tudo que eu preciso\nApenas um toque da Tua mão\nE tudo vai mudar\n\nEu não preciso de muito\nApenas um toque Teu\nUm toque do Teu poder\nUm toque do Teu amor\n\nApenas um toque, Senhor\nÉ tudo que eu preciso\nApenas um toque da Tua mão\nE tudo vai mudar\n\nToca-me, Senhor\nToca-me agora\nApenas um toque\nE tudo vai mudar",
  "tags": ["cura", "milagre", "fé", "toque de Deus"]
}
